cooaki-0.3.0.post2.dist-info/METADATA
cooaki-0.3.0.post2.dist-info/WHEEL
cooaki-0.3.0.post2.dist-info/entry_points.txt
cooaki-0.3.0.post2.dist-info/licenses/LICENSE
cooaki/__init__.py
cooaki/__main__.py
cooaki/akinator/__init__.py
cooaki/akinator/base.py
cooaki/akinator/httpx.py
cooaki/akinator/playwright.py
cooaki/const.py
cooaki/errors.py
cooaki-0.3.0.post2.dist-info/RECORD
