Metadata-Version: 2.1
Name: cooaki
Version: 0.3.0.post2
Summary: Another Async Akinator API Wrapper
Author-Email: LgCookie <lgc2333@126.com>
License: MIT
Project-URL: homepage, https://github.com/lgc2333/cooaki
Requires-Python: <4.0,>=3.9
Requires-Dist: httpx>=0.27.2
Requires-Dist: cookit[pyd]>=0.11.0
Provides-Extra: patchright
Requires-Dist: patchright>=1.51.3; extra == "patchright"
